flooder/__init__.py
flooder/cli.py
flooder/core.py
flooder/io.py
flooder/synthetic_data_generators.py
flooder/triton_kernels.py
flooder/datasets/__init__.py
flooder/datasets/datasets.py
flooder-1.0.dist-info/licenses/LICENSE
flooder-1.0.dist-info/METADATA
flooder-1.0.dist-info/WHEEL
flooder-1.0.dist-info/entry_points.txt
flooder-1.0.dist-info/top_level.txt
flooder-1.0.dist-info/RECORD
