Metadata-Version: 2.4
Name: flooder
Version: 1.0
Summary: Flood complex PH
Author: Paolo Pellizzoni, Florian Graf, Martin Uray, Stefan Huber, Roland Kwitt
Author-email: "Paolo Pellizzoni, Florian Graf, Martin Uray, Stefan Huber, Roland Kwitt" <roland.kwitt@gmail.com>
License-Expression: MIT
Requires-Python: >=3.8
License-File: LICENSE
Requires-Dist: torch
Requires-Dist: gudhi
Requires-Dist: numpy
Requires-Dist: gdown
Requires-Dist: zstandard
Requires-Dist: tqdm
Requires-Dist: pandas
Requires-Dist: fpsample
Requires-Dist: scipy
Requires-Dist: rich
Requires-Dist: rich_argparse
Dynamic: author
Dynamic: license-file
Dynamic: requires-python
